xfem/__init__.py
xfem/__init__.pyi
xfem/_version.py
xfem/_version.pyi
xfem/cutmg.py
xfem/lset_smoothblend.py
xfem/lset_spacetime.py
xfem/lsetcurv.py
xfem/mlset.py
xfem/ngs_check.py
xfem/utils.py
xfem/xfem.pyi
xfem/xfem.so
xfem-2.1.2506.data/data/include/SpaceTimeFE.hpp
xfem-2.1.2506.data/data/include/SpaceTimeFESpace.hpp
xfem-2.1.2506.data/data/include/aggregates.hpp
xfem-2.1.2506.data/data/include/bitarraycf.hpp
xfem-2.1.2506.data/data/include/calcpointshift.hpp
xfem-2.1.2506.data/data/include/cutinfo.hpp
xfem-2.1.2506.data/data/include/cutintegral.hpp
xfem-2.1.2506.data/data/include/diffopDt.hpp
xfem-2.1.2506.data/data/include/fieldeval.hpp
xfem-2.1.2506.data/data/include/ghostpenalty.hpp
xfem-2.1.2506.data/data/include/lsetintdomain.hpp
xfem-2.1.2506.data/data/include/lsetrefine.hpp
xfem-2.1.2506.data/data/include/mlsetintegration.hpp
xfem-2.1.2506.data/data/include/ngsxstd.hpp
xfem-2.1.2506.data/data/include/p1interpol.hpp
xfem-2.1.2506.data/data/include/projshift.hpp
xfem-2.1.2506.data/data/include/restrictedblf.hpp
xfem-2.1.2506.data/data/include/restrictedfespace.hpp
xfem-2.1.2506.data/data/include/sFESpace.hpp
xfem-2.1.2506.data/data/include/shiftedevaluate.hpp
xfem-2.1.2506.data/data/include/shiftintegrators.hpp
xfem-2.1.2506.data/data/include/spacetime_vtk.hpp
xfem-2.1.2506.data/data/include/spacetimecutrule.hpp
xfem-2.1.2506.data/data/include/straightcutrule.hpp
xfem-2.1.2506.data/data/include/symboliccutbfi.hpp
xfem-2.1.2506.data/data/include/symboliccutlfi.hpp
xfem-2.1.2506.data/data/include/timecf.hpp
xfem-2.1.2506.data/data/include/xFESpace.hpp
xfem-2.1.2506.data/data/include/xdecompose.hpp
xfem-2.1.2506.data/data/include/xfemdiffops.hpp
xfem-2.1.2506.data/data/include/xfiniteelement.hpp
xfem-2.1.2506.data/data/include/xintegration.hpp
xfem-2.1.2506.data/data/include/xprolongation.hpp
xfem-2.1.2506.data/data/share/ngsxfem/fictdom.py
xfem-2.1.2506.data/data/share/ngsxfem/fictdom_dg.py
xfem-2.1.2506.data/data/share/ngsxfem/fictdom_mlset.py
xfem-2.1.2506.dist-info/METADATA
xfem-2.1.2506.dist-info/WHEEL
xfem-2.1.2506.dist-info/licenses/LICENSE
xfem-2.1.2506.dist-info/RECORD
