Metadata-Version: 2.2
Name: xfem
Version: 2.1.2506
Summary: (ngs)xfem is an Add-on library to Netgen/NGSolve for unfitted/cut FEM.
Author-Email: Christoph Lehrenfeld <lehrenfeld@math.uni-goettingen.de>
Classifier: License :: OSI Approved :: GNU Lesser General Public License v3 (LGPLv3)
Project-URL: github, https://github.com/ngsxfem/ngsxfem
Requires-Python: >=3.9
Requires-Dist: ngsolve==6.2.2506
Provides-Extra: test
Requires-Dist: pytest; extra == "test"
